ulauncher_extension_generator/LICENSE
ulauncher_extension_generator/README.md
ulauncher_extension_generator/__init__.py
ulauncher_extension_generator/main.py
ulauncher_extension_generator/__pycache__/__init__.cpython-312.pyc
ulauncher_extension_generator/__pycache__/main.cpython-312.pyc
ulauncher_generator-0.1.3.dist-info/LICENSE
ulauncher_generator-0.1.3.dist-info/METADATA
ulauncher_generator-0.1.3.dist-info/WHEEL
ulauncher_generator-0.1.3.dist-info/entry_points.txt
ulauncher_generator-0.1.3.dist-info/top_level.txt
ulauncher_generator-0.1.3.dist-info/RECORD
