Metadata-Version: 2.1
Name: ulauncher-generator
Version: 0.1.3
Summary: A Ulauncher extension generator
Home-page: https://github.com/ubuntupunk/ulauncher-extension-generator
Author: ubuntupunk
Author-email: ubuntupunk@gmail.com
Classifier: Programming Language :: Python :: 3
Classifier: License :: OSI Approved :: MIT License
Classifier: Operating System :: POSIX :: Linux
Requires-Python: >=3.6
License-File: LICENSE
Provides-Extra: dev
Requires-Dist: pytest; extra == "dev"
Requires-Dist: pytest-cov; extra == "dev"
